yapsap/__init__.py
yapsap/factoring.py
yapsap/paramodulation.py
yapsap/py.typed
yapsap/reflexivity_resolution.py
yapsap/resolution.py
yapsap/resources/TPTP-mock/Problems/TST/TST001-1.p
yapsap/substitution.py
yapsap/unification.py
yapsap/utils.py
yapsap/yapsa_prover.py
yapsap-0.0.2.dist-info/LICENSE
yapsap-0.0.2.dist-info/METADATA
yapsap-0.0.2.dist-info/WHEEL
yapsap-0.0.2.dist-info/RECORD
