Metadata-Version: 2.1
Name: yapsap
Version: 0.0.2
Summary: Yet Another Python SAturation Prover
Home-page: https://github.com/inpefess/yapsap
License: Apache-2.0
Keywords: saturation-style proving,automated theorem proving,given clause algorithm
Author: Boris Shminke
Author-email: boris@shminke.com
Requires-Python: >=3.8.1,<3.12
Classifier: Development Status :: 1 - Planning
Classifier: Environment :: Console
Classifier: Intended Audience :: Science/Research
Classifier: License :: OSI Approved :: Apache Software License
Classifier: Natural Language :: English
Classifier: Operating System :: OS Independent
Classifier: Programming Language :: Python :: 3
Classifier: Programming Language :: Python :: 3.9
Classifier: Programming Language :: Python :: 3.10
Classifier: Programming Language :: Python :: 3.11
Classifier: Programming Language :: Python :: 3.7
Classifier: Programming Language :: Python :: 3.8
Classifier: Typing :: Typed
Requires-Dist: importlib_resources ; python_version < "3.9"
Requires-Dist: orjson
Requires-Dist: tptp-lark-parser
Project-URL: Repository, https://github.com/inpefess/yapsap
